crawlist/__init__.py
crawlist/__version__.py
crawlist/annotation.py
crawlist/analyzers/__init__.py
crawlist/analyzers/analyzer.py
crawlist/analyzers/driver.py
crawlist/analyzers/request.py
crawlist/analyzers/selector.py
crawlist/analyzers/trie.py
crawlist/analyzers/valid.py
crawlist/analyzers/pager/__init__.py
crawlist/analyzers/pager/dynamic_pager.py
crawlist/analyzers/pager/pager.py
crawlist/analyzers/pager/static_pager.py
crawlist/processings/__init__.py
crawlist/processings/action.py
crawlist/processings/script.py
crawlist-0.1.0.dist-info/LICENSE
crawlist-0.1.0.dist-info/METADATA
crawlist-0.1.0.dist-info/WHEEL
crawlist-0.1.0.dist-info/top_level.txt
crawlist-0.1.0.dist-info/RECORD
