Metadata-Version: 2.1
Name: crawlist
Version: 0.1.0
Summary: A universal solution for web crawling lists
Home-page: https://github.com/WwwwwyDev/crawlist
Author: WwyDev
Author-email: wwy20001014@foxmail.com
License: MIT
Classifier: License :: OSI Approved :: MIT License
Classifier: Programming Language :: Python
Classifier: Programming Language :: Python :: 3
Classifier: Programming Language :: Python :: 3.10
Classifier: Programming Language :: Python :: Implementation :: CPython
Classifier: Programming Language :: Python :: Implementation :: PyPy
Requires-Python: >=3.10.0
License-File: LICENSE
Requires-Dist: parsel
Requires-Dist: selenium >=4.0.0
Requires-Dist: cssselect
Requires-Dist: lxml
Requires-Dist: requests
Requires-Dist: webdriver-manager
